aws_cdk/asset_awscli_v2/__init__.py
aws_cdk/asset_awscli_v2/py.typed
aws_cdk/asset_awscli_v2/_jsii/__init__.py
aws_cdk/asset_awscli_v2/_jsii/asset-awscli-v2@2.0.160.jsii.tgz
aws_cdk_asset_awscli_v2-2.0.160.dist-info/LICENSE
aws_cdk_asset_awscli_v2-2.0.160.dist-info/METADATA
aws_cdk_asset_awscli_v2-2.0.160.dist-info/NOTICE
aws_cdk_asset_awscli_v2-2.0.160.dist-info/WHEEL
aws_cdk_asset_awscli_v2-2.0.160.dist-info/top_level.txt
aws_cdk_asset_awscli_v2-2.0.160.dist-info/RECORD
